dteenergybridge/__init__.py
dteenergybridge/dteenergybridge.py
dteenergybridge/exceptions.py
dteenergybridge-0.1.1.dist-info/DESCRIPTION.rst
dteenergybridge-0.1.1.dist-info/METADATA
dteenergybridge-0.1.1.dist-info/RECORD
dteenergybridge-0.1.1.dist-info/WHEEL
dteenergybridge-0.1.1.dist-info/metadata.json
dteenergybridge-0.1.1.dist-info/top_level.txt
