Metadata-Version: 2.0
Name: dteenergybridge
Version: 0.1.1
Summary: Library for retrieving data from a DTE Energy Bridge
Home-page: https://github.com/kylehendricks/dteenergybridge
Author: Kyle John Hendricks
Author-email: kyle@hendricks.nu
License: MIT license
Keywords: dteenergybridge
Platform: UNKNOWN
Classifier: Development Status :: 2 - Pre-Alpha
Classifier: Intended Audience :: Developers
Classifier: License :: OSI Approved :: MIT License
Classifier: Natural Language :: English
Classifier: Programming Language :: Python :: 3
Classifier: Programming Language :: Python :: 3.4
Classifier: Programming Language :: Python :: 3.5
Classifier: Programming Language :: Python :: 3.6
Requires-Dist: requests
